nazca/__init__.py
nazca/__pkginfo__.py
nazca/data/__init__.py
nazca/data/countries.py
nazca/data/countries_iso_3166.txt
nazca/data/french_lemmas.txt
nazca/data/stopwords.py
nazca/data/us_states.py
nazca/ner/__init__.py
nazca/ner/filters.py
nazca/ner/preprocessors.py
nazca/ner/sources.py
nazca/rl/__init__.py
nazca/rl/aligner.py
nazca/rl/blocking.py
nazca/utils/__init__.py
nazca/utils/dataio.py
nazca/utils/distances.py
nazca/utils/minhashing.py
nazca/utils/normalize.py
nazca/utils/tokenizer.py
nazca-3.2.1.dist-info/METADATA
nazca-3.2.1.dist-info/WHEEL
nazca-3.2.1.dist-info/top_level.txt
nazca-3.2.1.dist-info/RECORD
