Metadata-Version: 2.1
Name: nazca
Version: 3.2.1
Summary: Python library for data alignment
Home-page: https://forge.extranet.logilab.fr/open-source/nazca
Author: Logilab
Author-email: contact@logilab.fr
License: LGPL
Classifier: Programming Language :: Python
Classifier: Programming Language :: Python :: 3
Classifier: Programming Language :: Python :: 3 :: Only
Classifier: Topic :: Scientific/Engineering :: Information Analysis
Classifier: Topic :: Software Development :: Libraries :: Python Modules
Classifier: Topic :: Text Processing
Requires-Dist: python-dateutil
Requires-Dist: lxml <6.0.0,>=4.0.0
Requires-Dist: numpy
Requires-Dist: scipy
Requires-Dist: scikit-learn
Provides-Extra: llm
Requires-Dist: langchain <0.2.0,>=0.1.4 ; extra == 'llm'
Requires-Dist: faiss-cpu <2.0.0,>=1.7.4 ; extra == 'llm'
Requires-Dist: sentence-transformers >=3.0.0 ; extra == 'llm'
